{"lastUsed":1655073622737,"path":"C:\/Users\/Yuri Sparda\/Desktop\/java eclipse","projectCount":27,"recentFiles":[{"path":"\/cifra de cezar\/src","parentWorkspace":"C:\/Users\/Yuri Sparda\/Desktop\/java eclipse","name":"main.java","lastModified":1654957007791,"locationURI":"file:\/C:\/Users\/Yuri%20Sparda\/Desktop\/java%20eclipse\/cifra%20de%20cezar\/src\/main.java"},{"path":"\/Equação 2° Grau Girard\/src","parentWorkspace":"C:\/Users\/Yuri Sparda\/Desktop\/java eclipse","name":"Main.java","lastModified":1655060386635,"locationURI":"file:\/C:\/Users\/Yuri%20Sparda\/Desktop\/java%20eclipse\/Equação%202°%20Grau%20Girard\/src\/Main.java"}]}